AUTHORS.rst
CONTRIBUTING.rst
HISTORY.rst
LICENSE
MANIFEST.in
README.rst
TODO.rst
requirements.txt
setup.py
airframe/__init__.py
airframe/airframe.py
airframe/flashair.py
airframe/flickr.py
airframe/version.py
airframe.egg-info/PKG-INFO
airframe.egg-info/SOURCES.txt
airframe.egg-info/dependency_links.txt
airframe.egg-info/entry_points.txt
airframe.egg-info/requires.txt
airframe.egg-info/top_level.txt
airframe.egg-info/zip-safe
tests/__init__.py
tests/test_airframe.py