Metadata-Version: 1.1
Name: airframe
Version: 0.2.0
Summary: Push images to a Toshiba FlashAir Wifi SD card
Home-page: https://github.com/virantha/airframe
Author: Virantha N. Ekanayake
Author-email: virantha@gmail.com
License: ASL2
Keywords: airframe
Platform: UNKNOWN
Classifier: Development Status :: 2 - Pre-Alpha
Classifier: Natural Language :: English
Classifier: Programming Language :: Python :: 2.7
